recommends/__init__.py
recommends/apps.py
recommends/converters.py
recommends/managers.py
recommends/models.py
recommends/settings.py
recommends/similarities.py
recommends/tasks.py
recommends/utils.py
recommends/algorithms/__init__.py
recommends/algorithms/base.py
recommends/algorithms/ghetto.py
recommends/algorithms/naive.py
recommends/algorithms/pyrecsys.py
recommends/management/__init__.py
recommends/management/commands/__init__.py
recommends/management/commands/recommends_precompute.py
recommends/providers/__init__.py
recommends/storages/__init__.py
recommends/storages/base.py
recommends/storages/djangoorm/__init__.py
recommends/storages/djangoorm/admin.py
recommends/storages/djangoorm/managers.py
recommends/storages/djangoorm/models.py
recommends/storages/djangoorm/routers.py
recommends/storages/djangoorm/settings.py
recommends/storages/djangoorm/storage.py
recommends/storages/djangoorm/migrations/0001_initial.py
recommends/storages/djangoorm/migrations/0002_auto_20141013_2311.py
recommends/storages/djangoorm/migrations/__init__.py
recommends/storages/mongodb/__init__.py
recommends/storages/mongodb/managers.py
recommends/storages/mongodb/settings.py
recommends/storages/mongodb/storage.py
recommends/storages/redis/__init__.py
recommends/storages/redis/managers.py
recommends/storages/redis/settings.py
recommends/storages/redis/storage.py
recommends/templatetags/__init__.py
recommends/templatetags/recommends.py
recommends/tests/__init__.py
recommends/tests/admin.py
recommends/tests/models.py
recommends/tests/recommendations.py
recommends/tests/runtests.py
recommends/tests/settings.py
recommends/tests/tests.py
recommends/tests/urls.py
recommends/tests/views.py
django_recommends-1.0.0.dist-info/AUTHORS
django_recommends-1.0.0.dist-info/LICENSE
django_recommends-1.0.0.dist-info/METADATA
django_recommends-1.0.0.dist-info/WHEEL
django_recommends-1.0.0.dist-info/top_level.txt
django_recommends-1.0.0.dist-info/RECORD
