Metadata-Version: 2.1
Name: django-recommends
Version: 1.0.0
Summary: A django app that builds item-based suggestions for users
Home-page: https://github.com/python-recsys/django-recommends
Author: Flavio Curella
Author-email: flavio.curella@gmail.com
License: MIT
Platform: UNKNOWN
Classifier: Development Status :: 4 - Beta
Classifier: Environment :: Console
Classifier: Intended Audience :: Developers
Classifier: Intended Audience :: Information Technology
Classifier: License :: OSI Approved :: MIT License
Classifier: Operating System :: OS Independent
Classifier: Programming Language :: Python :: 3.6
Classifier: Programming Language :: Python :: 3.7
Classifier: Programming Language :: Python :: 3.8
Classifier: Framework :: Django
Classifier: Topic :: Scientific/Engineering :: Information Analysis
Requires-Dist: Django (>=1.7)
Requires-Dist: celery (>=3.0)
Requires-Dist: python-dateutil (>=2.1)
